itrx/__init__.py
itrx/itr.py
itrx/py.typed
itrx-0.2.1.dist-info/METADATA
itrx-0.2.1.dist-info/WHEEL
itrx-0.2.1.dist-info/entry_points.txt
itrx-0.2.1.dist-info/licenses/LICENCE.md
itrx-0.2.1.dist-info/RECORD
