Metadata-Version: 2.4
Name: itrx
Version: 0.2.1
Summary: A chainable iterator adapter
Project-URL: Homepage, https://github.com/virgesmith/itrx
Project-URL: Bug Tracker, https://github.com/virgesmith/itrx/issues
Author-email: virgesmith <andrew@friarswood.net>
License-Expression: MIT
License-File: LICENCE.md
Classifier: Operating System :: OS Independent
Classifier: Programming Language :: Python :: 3.12
Classifier: Programming Language :: Python :: 3.13
Classifier: Programming Language :: Python :: 3.14
Requires-Python: >=3.12
